{
  "required": true,
  "minVersion": "0.8",
  "package": "com.kyanite.deeperdarker.mixin",
  "compatibilityLevel": "JAVA_17",
  "mixins": [
    "containers.ChestEntityMixin",
    "containers.ContainerMixin",
    "entities.PhantomMixin",
    "misc.SculkSpreadMixin",
    "containers.StonecutterMixin",
    "misc.VibrationListenerMixin",
    "entities.WardenMixin",
    "misc.SculkBlockMixin"
  ],
  "client": [
    "client.WardenAnimations",
    "client.PhantomRendererMixin"
  ],
  "injectors": {
    "defaultRequire": 1
  }
}