{
  "credit": "Made with Blockbench",
  "parent": "builtin/entity",
  "textures": {
    "particle": "minecraft:block/oak_planks"
  },
  "texture_size": [
    64,
    64
  ],
  "display": {
    "thirdperson_righthand": {
      "scale": [
        0.3,
        0.3,
        0.3
      ]
    },
    "thirdperson_lefthand": {
      "scale": [
        0.3,
        0.3,
        0.3
      ]
    },
    "firstperson_righthand": {
      "rotation": [
        0,
        14,
        0
      ],
      "translation": [
        -2.25,
        -1.25,
        0
      ],
      "scale": [
        0.4,
        0.4,
        0.4
      ]
    },
    "firstperson_lefthand": {
      "rotation": [
        0,
        14,
        0
      ],
      "translation": [
        0,
        -1.25,
        0
      ],
      "scale": [
        0.4,
        0.4,
        0.4
      ]
    },
    "ground": {
      "scale": [
        0.5,
        0.5,
        0.5
      ]
    },
    "gui": {
      "rotation": [
        21,
        -137,
        0
      ],
      "translation": [
        0.25,
        -5.25,
        0
      ],
      "scale": [
        0.7,
        0.7,
        0.7
      ]
    },
    "head": {
      "translation": [
        0,
        -6.5,
        0
      ]
    },
    "fixed": {
      "translation": [
        0,
        -7.25,
        6.25
      ]
    }
  }
}